quyk/__init__.py
quyk/cli_test.py
quyk/core.py
quyk/core.py.save
quyk-0.1.1.dist-info/LICENSE.txt
quyk-0.1.1.dist-info/METADATA
quyk-0.1.1.dist-info/WHEEL
quyk-0.1.1.dist-info/entry_points.txt
quyk-0.1.1.dist-info/RECORD
